{
  "@context": "https://w3id.org/ro/crate/1.1/context",
  "@graph": [
    {
      "@id": "ro-crate-metadata.json",
      "@type": "CreativeWork",
      "conformsTo": {
        "@id": "https://w3id.org/ro/crate/1.1"
      },
      "about": {
        "@id": "./"
      }
    },
    {
      "@id": "./",
      "@type": "Dataset",
      "name": "UrbanHistory4D – City of Dresden 4D Browser Subcollection",
      "description": "Subset der Enhanced Publication UrbanHistory4D mit Fokus auf der Stadt Dresden. Enthält Webapplikation (4D Browser), Karten, 3D-Modelle, Fotos, Datenbank, Emulation und Interaktionsvideo.",
      "license": "https://creativecommons.org/licenses/by/4.0/",
      "hasPart": [
        {
          "@id": "webapp/"
        },
        {
          "@id": "website/"
        }
      ]
    },
    {
      "@id": "webapp/",
      "@type": "Dataset",
      "name": "UrbanHistory4D 4D Browser Web App (Dresden)",
      "isPartOf": {
        "@id": "./"
      },
      "hasPart": [
        {
          "@id": "webapp/buildings/"
        },
        {
          "@id": "webapp/database/"
        },
        {
          "@id": "webapp/emulation/"
        },
        {
          "@id": "webapp/interaction_video/"
        },
        {
          "@id": "webapp/maps/"
        },
        {
          "@id": "webapp/photos/"
        },
        {
          "@id": "webapp/related_articles/"
        }
      ]
    },
    {
      "@id": "website/",
      "@type": "Dataset",
      "name": "UrbanHistory4D Projektwebsite (reduzierte HTML5-Version)",
      "isPartOf": {
        "@id": "./"
      },
      "hasPart": [
        {
          "@id": "website/assets/"
        },
        {
          "@id": "website/index.html"
        },
        {
          "@id": "website/about.html"
        },
        {
          "@id": "website/contact.html"
        },
        {
          "@id": "website/explore4d.html"
        },
        {
          "@id": "website/partners.html"
        },
        {
          "@id": "website/publications.html"
        },
        {
          "@id": "website/workshop.html"
        }
      ]
    },
    {
      "@id": "webapp/buildings/",
      "@type": "Dataset",
      "name": "3D-Modelle rekonstruierter Architektur (glTF)",
      "isPartOf": {
        "@id": "webapp/"
      },
      "hasPart": [
        {
          "@id": "webapp/buildings/building_0001/building_0001.gltf"
        },
        {
          "@id": "webapp/buildings/building_0001/building_0001.bin"
        },
        {
          "@id": "webapp/buildings/building_0001/building_0001.png"
        },
        {
          "@id": "webapp/buildings/building_0002/building_0002.gltf"
        },
        {
          "@id": "webapp/buildings/building_0002/building_0002.bin"
        },
        {
          "@id": "webapp/buildings/building_0002/building_0002.png"
        }
      ]
    },
    {
      "@id": "webapp/database/",
      "@type": "Dataset",
      "name": "Datenbankexport der UrbanHistory4D-Applikation",
      "isPartOf": {
        "@id": "webapp/"
      },
      "hasPart": [
        {
          "@id": "webapp/database/urbanhistory4d.siard"
        }
      ]
    },
    {
      "@id": "webapp/emulation/",
      "@type": "Dataset",
      "name": "Emulationsumgebung (QCOW2) und Dokumentation",
      "isPartOf": {
        "@id": "webapp/"
      },
      "hasPart": [
        {
          "@id": "webapp/emulation/urbanhistory4d.qcow2"
        },
        {
          "@id": "webapp/emulation/run_instructions.txt"
        },
        {
          "@id": "webapp/emulation/browser_version.txt"
        }
      ]
    },
    {
      "@id": "webapp/interaction_video/",
      "@type": "Dataset",
      "name": "Videodokumentation der Interaktion",
      "isPartOf": {
        "@id": "webapp/"
      },
      "hasPart": [
        {
          "@id": "webapp/interaction_video/interaction_dresden.mkv"
        }
      ]
    },
    {
      "@id": "webapp/maps/",
      "@type": "Dataset",
      "name": "Kartenmaterial (GeoTIFF)",
      "isPartOf": {
        "@id": "webapp/"
      },
      "hasPart": [
        {
          "@id": "webapp/maps/base_map_0001.tif"
        },
        {
          "@id": "webapp/maps/base_map_0002.tif"
        }
      ]
    },
    {
      "@id": "webapp/photos/",
      "@type": "Dataset",
      "name": "Wissenschaftlich relevante Fotos (TIFF)",
      "isPartOf": {
        "@id": "webapp/"
      },
      "hasPart": [
        {
          "@id": "webapp/photos/photo_0001.tiff"
        },
        {
          "@id": "webapp/photos/photo_0002.tiff"
        },
        {
          "@id": "webapp/photos/photo_0003.tiff"
        },
        {
          "@id": "webapp/photos/photo_0004.tiff"
        }
      ]
    },
    {
      "@id": "webapp/related_articles/",
      "@type": "Dataset",
      "name": "Zugehörige Artikel (PDF/A-3)",
      "isPartOf": {
        "@id": "webapp/"
      },
      "hasPart": [
        {
          "@id": "webapp/related_articles/article_0001.pdf"
        },
        {
          "@id": "webapp/related_articles/article_0002.pdf"
        }
      ]
    },
    {
      "@id": "website/assets/",
      "@type": "Dataset",
      "name": "Website-Assets (Bilder, Video)",
      "isPartOf": {
        "@id": "website/"
      },
      "hasPart": [
        {
          "@id": "website/assets/images/"
        },
        {
          "@id": "website/assets/video/"
        }
      ]
    },
    {
      "@id": "website/assets/images/",
      "@type": "Dataset",
      "name": "Website-Bilder & Logos",
      "isPartOf": {
        "@id": "website/assets/"
      },
      "hasPart": [
        {
          "@id": "website/assets/images/image_0001.png"
        },
        {
          "@id": "website/assets/images/image_0002.png"
        }
      ]
    },
    {
      "@id": "website/assets/video/",
      "@type": "Dataset",
      "name": "Eingebettetes Tutorial-Video",
      "isPartOf": {
        "@id": "website/assets/"
      },
      "hasPart": [
        {
          "@id": "website/assets/video/subtitles.vtt"
        },
        {
          "@id": "website/assets/video/tutorial_video.mkv"
        }
      ]
    },
    {
      "@id": "webapp/buildings/building_0001/building_0001.gltf",
      "@type": [
        "File",
        "3DModel"
      ],
      "name": "3D-Modell Gebäude 0001 (Dresden)",
      "encodingFormat": "model/gltf+json",
      "isPartOf": {
        "@id": "webapp/buildings/"
      }
    },
    {
      "@id": "webapp/buildings/building_0001/building_0001.bin",
      "@type": "File",
      "name": "Binärdaten 3D-Modell Gebäude 0001",
      "encodingFormat": "application/octet-stream",
      "isPartOf": {
        "@id": "webapp/buildings/"
      }
    },
    {
      "@id": "webapp/buildings/building_0001/building_0001.png",
      "@type": [
        "File",
        "ImageObject"
      ],
      "name": "Textur 3D-Modell Gebäude 0001",
      "encodingFormat": "image/png",
      "isPartOf": {
        "@id": "webapp/buildings/"
      }
    },
    {
      "@id": "webapp/buildings/building_0002/building_0002.gltf",
      "@type": [
        "File",
        "3DModel"
      ],
      "name": "3D-Modell Gebäude 0002 (Dresden)",
      "encodingFormat": "model/gltf+json",
      "isPartOf": {
        "@id": "webapp/buildings/"
      }
    },
    {
      "@id": "webapp/buildings/building_0002/building_0002.bin",
      "@type": "File",
      "name": "Binärdaten 3D-Modell Gebäude 0002",
      "encodingFormat": "application/octet-stream",
      "isPartOf": {
        "@id": "webapp/buildings/"
      }
    },
    {
      "@id": "webapp/buildings/building_0002/building_0002.png",
      "@type": [
        "File",
        "ImageObject"
      ],
      "name": "Textur 3D-Modell Gebäude 0002",
      "encodingFormat": "image/png",
      "isPartOf": {
        "@id": "webapp/buildings/"
      }
    },
    {
      "@id": "webapp/database/urbanhistory4d.siard",
      "@type": "File",
      "name": "UrbanHistory4D-Datenbank (SIARD-Archiv)",
      "encodingFormat": "application/siard",
      "isPartOf": {
        "@id": "webapp/database/"
      }
    },
    {
      "@id": "webapp/emulation/urbanhistory4d.qcow2",
      "@type": [
        "File",
        "SoftwareApplication"
      ],
      "name": "Emulations-Image der UrbanHistory4D-Umgebung (QCOW2)",
      "encodingFormat": "application/x-qemu-disk",
      "isPartOf": {
        "@id": "webapp/emulation/"
      }
    },
    {
      "@id": "webapp/emulation/run_instructions.txt",
      "@type": "File",
      "name": "Startanleitung für Emulationsumgebung",
      "encodingFormat": "text/plain",
      "isPartOf": {
        "@id": "webapp/emulation/"
      }
    },
    {
      "@id": "webapp/emulation/browser_version.txt",
      "@type": "File",
      "name": "Dokumentation der Browser- und WebGL-Fähigkeiten",
      "encodingFormat": "text/plain",
      "isPartOf": {
        "@id": "webapp/emulation/"
      }
    },
    {
      "@id": "webapp/interaction_video/interaction_dresden.mkv",
      "@type": [
        "File",
        "MediaObject"
      ],
      "name": "Interaktionsvideo UrbanHistory4D – Dresden",
      "encodingFormat": "video/x-matroska",
      "isPartOf": {
        "@id": "webapp/interaction_video/"
      }
    },
    {
      "@id": "webapp/maps/base_map_0001.tif",
      "@type": [
        "File",
        "ImageObject"
      ],
      "name": "Basiskarte Dresden 0001 (GeoTIFF)",
      "encodingFormat": "image/tiff",
      "spatialCoverage": "Dresden, Germany",
      "isPartOf": {
        "@id": "webapp/maps/"
      }
    },
    {
      "@id": "webapp/maps/base_map_0002.tif",
      "@type": [
        "File",
        "ImageObject"
      ],
      "name": "Basiskarte Dresden 0002 (GeoTIFF)",
      "encodingFormat": "image/tiff",
      "spatialCoverage": "Dresden, Germany",
      "isPartOf": {
        "@id": "webapp/maps/"
      }
    },
    {
      "@id": "webapp/photos/photo_0001.tiff",
      "@type": [
        "File",
        "ImageObject"
      ],
      "name": "Salzgasse mit Frauenkirche",
      "creator": "Unknown Photographer",
      "dateCreated": "1886",
      "encodingFormat": "image/tiff",
      "spatialCoverage": "Dresden, Germany",
      "identifier": "df_hauptkatalog_0084634",
      "isPartOf": {
        "@id": "webapp/photos/"
      },
      "contentUrl": "http://www.deutschefotothek.de/documents/obj/80817531",
      "sameAs": "https://iiif.arthistoricum.net/proxy/fotothek/df_hauptkatalog_0084634/manifest.json",
      "note": "Digitised 9x12cm glass negative, 600 dpi, 16 bit per channel, uncompressed TIFF with embedded ICC profile.",
      "preservationState": "preserved",
      "preservationInfo": {
        "@id": "http://www.deutschefotothek.de",
        "isil": "DE-2396",
        "name": "SLUBArchiv.digital",
        "identifier": "df_hauptkatalog_0084634_120000000000001"
      }
    },
    {
      "@id": "webapp/photos/photo_0002.tiff",
      "@type": [
        "File",
        "ImageObject"
      ],
      "name": "Frauenkirche",
      "creator": "Ermenegildo Antonio Donadini",
      "dateCreated": "1888",
      "encodingFormat": "image/tiff",
      "spatialCoverage": "Dresden, Germany",
      "identifier": "df_hauptkatalog_0041697",
      "isPartOf": {
        "@id": "webapp/photos/"
      },
      "contentUrl": "http://www.deutschefotothek.de/documents/obj/80817431",
      "sameAs": "https://iiif.arthistoricum.net/proxy/fotothek/df_hauptkatalog_0041697/manifest.json",
      "note": "Digitised 9x12cm glass negative, TIFF 16bit, 600 dpi, uncompressed, ICC profile embedded.",
      "preservationState": "preserved",
      "preservationInfo": {
        "@id": "http://www.deutschefotothek.de",
        "isil": "DE-2396",
        "name": "SLUBArchiv.digital",
        "identifier": "df_hauptkatalog_0041697_120000000000001"
      }
    },
    {
      "@id": "webapp/photos/photo_0003.tiff",
      "@type": [
        "File",
        "ImageObject"
      ],
      "name": "Fassade zur Wilsdruffer Straße mit Gedenkstätte Busmannkapelle",
      "creator": "Andrea Kiehn",
      "dateCreated": "2013-05-11",
      "encodingFormat": "image/tiff",
      "spatialCoverage": "Dresden, Germany",
      "identifier": "tu_kg_0189515",
      "isPartOf": {
        "@id": "webapp/photos/"
      },
      "contentUrl": "http://www.deutschefotothek.de/documents/obj/90058526-tud",
      "sameAs": "https://iiif.arthistoricum.net/proxy/fotothek/tu_kg_0189515/manifest.json",
      "note": "Born-digital photograph to be migrated to archival TIFF format prior to ingestion.",
      "preservationState": "pending",
      "preservationInfo": {
        "@id": "http://www.deutschefotothek.de",
        "isil": "DE-2396",
        "name": "SLUBArchiv.digital",
        "identifier": "tu_kg_0189515_120000000000002"
      }
    },
    {
      "@id": "webapp/photos/photo_0004.tiff",
      "@type": [
        "File",
        "ImageObject"
      ],
      "name": "Fassade zur Wilsdruffer Straße mit Gedenkstätte Busmannkapelle",
      "creator": "Andrea Kiehn",
      "dateCreated": "2013-05-11",
      "encodingFormat": "image/tiff",
      "spatialCoverage": "Dresden, Germany",
      "identifier": "tu_kg_0189510",
      "isPartOf": {
        "@id": "webapp/photos/"
      },
      "contentUrl": "http://www.deutschefotothek.de/documents/obj/90058521-tud",
      "sameAs": "https://iiif.arthistoricum.net/proxy/fotothek/tu_kg_0189510/manifest.json",
      "note": "Born-digital photograph to be migrated to archival TIFF format prior to ingestion.",
      "preservationState": "pending",
      "preservationInfo": {
        "@id": "http://www.deutschefotothek.de",
        "isil": "DE-2396",
        "name": "SLUBArchiv.digital",
        "identifier": "tu_kg_0189510_120000000000002"
      }
    },
    {
      "@id": "webapp/related_articles/article_0001.pdf",
      "@type": [
        "File",
        "CreativeWork"
      ],
      "name": "Zugehöriger Artikel 0001 (PDF/A-3)",
      "encodingFormat": "application/pdf",
      "isPartOf": {
        "@id": "webapp/related_articles/"
      }
    },
    {
      "@id": "webapp/related_articles/article_0002.pdf",
      "@type": [
        "File",
        "CreativeWork"
      ],
      "name": "Zugehöriger Artikel 0002 (PDF/A-3)",
      "encodingFormat": "application/pdf",
      "isPartOf": {
        "@id": "webapp/related_articles/"
      }
    },
    {
      "@id": "website/index.html",
      "@type": [
        "File",
        "CreativeWork"
      ],
      "name": "UrbanHistory4D – Startseite",
      "encodingFormat": "text/html",
      "isPartOf": {
        "@id": "website/"
      }
    },
    {
      "@id": "website/about.html",
      "@type": [
        "File",
        "CreativeWork"
      ],
      "name": "Über das Projekt",
      "encodingFormat": "text/html",
      "isPartOf": {
        "@id": "website/"
      }
    },
    {
      "@id": "website/contact.html",
      "@type": [
        "File",
        "CreativeWork"
      ],
      "name": "Kontakt & Provenienz",
      "encodingFormat": "text/html",
      "isPartOf": {
        "@id": "website/"
      }
    },
    {
      "@id": "website/explore4d.html",
      "@type": [
        "File",
        "CreativeWork"
      ],
      "name": "Erklärseite 4D Browser (mit Link zur Emulation)",
      "encodingFormat": "text/html",
      "isPartOf": {
        "@id": "website/"
      }
    },
    {
      "@id": "website/partners.html",
      "@type": [
        "File",
        "CreativeWork"
      ],
      "name": "Projektpartner",
      "encodingFormat": "text/html",
      "isPartOf": {
        "@id": "website/"
      }
    },
    {
      "@id": "website/publications.html",
      "@type": [
        "File",
        "CreativeWork"
      ],
      "name": "Publikationen",
      "encodingFormat": "text/html",
      "isPartOf": {
        "@id": "website/"
      }
    },
    {
      "@id": "website/workshop.html",
      "@type": [
        "File",
        "CreativeWork"
      ],
      "name": "Workshops",
      "encodingFormat": "text/html",
      "isPartOf": {
        "@id": "website/"
      }
    },
    {
      "@id": "website/assets/images/image_0001.png",
      "@type": [
        "File",
        "ImageObject"
      ],
      "name": "Website-Bild 0001",
      "encodingFormat": "image/png",
      "isPartOf": {
        "@id": "website/assets/images/"
      }
    },
    {
      "@id": "website/assets/images/image_0002.png",
      "@type": [
        "File",
        "ImageObject"
      ],
      "name": "Website-Bild 0002",
      "encodingFormat": "image/png",
      "isPartOf": {
        "@id": "website/assets/images/"
      }
    },
    {
      "@id": "website/assets/video/subtitles.vtt",
      "@type": "File",
      "name": "Untertiteldatei Tutorial-Video",
      "encodingFormat": "text/vtt",
      "isPartOf": {
        "@id": "website/assets/video/"
      }
    },
    {
      "@id": "website/assets/video/tutorial_video.mkv",
      "@type": [
        "File",
        "MediaObject"
      ],
      "name": "Tutorial-Video zur Nutzung des 4D Browsers",
      "encodingFormat": "video/x-matroska",
      "isPartOf": {
        "@id": "website/assets/video/"
      }
    },
    {
      "@id": "http://www.deutschefotothek.de",
      "@type": "Organization",
      "name": "Deutsche Fotothek / SLUBArchiv.digital",
      "identifier": "DE-2396",
      "isil": "DE-2396"
    }
  ]
}